subauto/__init__.py
subauto/cli.py
subauto/config/__init__.py
subauto/config/api_manager.py
subauto/config/settings.py
subauto/exceptions/__init__.py
subauto/exceptions/api_manager.py
subauto/exceptions/base.py
subauto/exceptions/conversion.py
subauto/exceptions/gemini.py
subauto/models/__init__.py
subauto/models/progress.py
subauto/utils/__init__.py
subauto/utils/logging.py
subauto/utils/utils.py
subauto-0.0.4.dist-info/METADATA
subauto-0.0.4.dist-info/WHEEL
subauto-0.0.4.dist-info/entry_points.txt
subauto-0.0.4.dist-info/licenses/LICENSE
subauto-0.0.4.dist-info/RECORD
