Metadata-Version: 2.4
Name: subauto
Version: 0.0.4
Summary: Add your description here
Project-URL: Homepage, https://github.com/ricjuanflores/subauto
Project-URL: Repository, https://github.com/ricjuanflores/subauto
Project-URL: Issues, https://github.com/ricjuanflores/subauto/issues
Author-email: Juan Flores <juanflores.ric@gmail.com>
License: MIT License
License-File: LICENSE
Requires-Python: >=3.11
Requires-Dist: ffmpeg-python>=0.2.0
Requires-Dist: google-genai>=0.3.0
Requires-Dist: openai-whisper>=20240930
Requires-Dist: rich>=13.9.4
Requires-Dist: srt>=3.5.3
Requires-Dist: typer>=0.13.0
